brynq_sdk_sodeco/__init__.py
brynq_sdk_sodeco/absencenote.py
brynq_sdk_sodeco/absences.py
brynq_sdk_sodeco/address.py
brynq_sdk_sodeco/base.py
brynq_sdk_sodeco/car.py
brynq_sdk_sodeco/communication.py
brynq_sdk_sodeco/contract.py
brynq_sdk_sodeco/costcentres.py
brynq_sdk_sodeco/department.py
brynq_sdk_sodeco/dimona.py
brynq_sdk_sodeco/divergentpayment.py
brynq_sdk_sodeco/divergentsalary.py
brynq_sdk_sodeco/documents.py
brynq_sdk_sodeco/family.py
brynq_sdk_sodeco/leavecounters.py
brynq_sdk_sodeco/modifications.py
brynq_sdk_sodeco/nssocat.py
brynq_sdk_sodeco/parcom.py
brynq_sdk_sodeco/prestations.py
brynq_sdk_sodeco/profcat.py
brynq_sdk_sodeco/replacement.py
brynq_sdk_sodeco/salarycomposition.py
brynq_sdk_sodeco/schedule.py
brynq_sdk_sodeco/tax.py
brynq_sdk_sodeco/worker.py
brynq_sdk_sodeco/schemas/__init__.py
brynq_sdk_sodeco/schemas/absence.py
brynq_sdk_sodeco/schemas/absencenote.py
brynq_sdk_sodeco/schemas/address.py
brynq_sdk_sodeco/schemas/car.py
brynq_sdk_sodeco/schemas/communication.py
brynq_sdk_sodeco/schemas/contract.py
brynq_sdk_sodeco/schemas/costcentre.py
brynq_sdk_sodeco/schemas/dimona.py
brynq_sdk_sodeco/schemas/divergentpayment.py
brynq_sdk_sodeco/schemas/document.py
brynq_sdk_sodeco/schemas/family.py
brynq_sdk_sodeco/schemas/prestation.py
brynq_sdk_sodeco/schemas/pydantic_contract.py
brynq_sdk_sodeco/schemas/replacement.py
brynq_sdk_sodeco/schemas/salarycomposition.py
brynq_sdk_sodeco/schemas/schedule.py
brynq_sdk_sodeco/schemas/tax.py
brynq_sdk_sodeco/schemas/worker.py
brynq_sdk_sodeco-4.1.2.dev4.dist-info/METADATA
brynq_sdk_sodeco-4.1.2.dev4.dist-info/WHEEL
brynq_sdk_sodeco-4.1.2.dev4.dist-info/top_level.txt
brynq_sdk_sodeco-4.1.2.dev4.dist-info/RECORD
