Metadata-Version: 2.4
Name: brynq_sdk_sodeco
Version: 4.1.2.dev4
Summary: Sodeco wrapper from BrynQ
Author: BrynQ
Author-email: support@brynq.com
License: BrynQ License
Requires-Dist: brynq-sdk-brynq<5,>=4
Requires-Dist: brynq-sdk-functions>=2
Requires-Dist: pandera>=0.18.0
Dynamic: author
Dynamic: author-email
Dynamic: description
Dynamic: license
Dynamic: requires-dist
Dynamic: summary
